{
  "北京": {
    "地区": "北京",
    "2019年": 0,
    "2018年": 0,
    "2017年": 0,
    "2016年": 0,
    "2015年": 0,
    "2014年": 0,
    "2013年": 0,
    "2012年": 0,
    "2011年": 0,
    "2010年": 0,
    "2009年": 0,
    "2008年": 0,
    "2007年": 0,
    "2006年": 0,
    "2005年": 0,
    "2004年": 0,
    "2003年": 0,
    "2002年": 0,
    "2001年": 0,
    "2000年": 0,
    "北京": "北京"
  },
  "天津": {
    "地区": "天津",
    "2019年": 0,
    "2018年": 0,
    "2017年": 0,
    "2016年": 0,
    "2015年": 0,
    "2014年": 0,
    "2013年": 0,
    "2012年": 0,
    "2011年": 0,
    "2010年": 0,
    "2009年": 0,
    "2008年": 0,
    "2007年": 0,
    "2006年": 0,
    "2005年": 0,
    "2004年": 0,
    "2003年": 0,
    "2002年": 0,
    "2001年": 0,
    "2000年": 0,
    "天津": "天津"
  },
  "河北": {
    "地区": "河北",
    "2019年": 0,
    "2018年": 0.1,
    "2017年": 0,
    "2016年": 0,
    "2015年": 0,
    "2014年": 0,
    "2013年": 0,
    "2012年": 0,
    "2011年": 0,
    "2010年": 0.03,
    "2009年": 0,
    "2008年": 0,
    "2007年": 0,
    "2006年": 0,
    "2005年": 0,
    "2004年": 0,
    "2003年": 0,
    "2002年": 0,
    "2001年": 0,
    "2000年": 0,
    "河北": "河北"
  },
  "山西": {
    "地区": "山西",
    "2019年": 0,
    "2018年": 0,
    "2017年": 0,
    "2016年": 0,
    "2015年": 0,
    "2014年": 0,
    "2013年": 0,
    "2012年": 0,
    "2011年": 0,
    "2010年": 0,
    "2009年": 0,
    "2008年": 0,
    "2007年": 0,
    "2006年": 0,
    "2005年": 0,
    "2004年": 0,
    "2003年": 0,
    "2002年": 0,
    "2001年": 0,
    "2000年": 0,
    "山西": "山西"
  },
  "内蒙古": {
    "地区": "内蒙古",
    "2019年": 0,
    "2018年": 0,
    "2017年": 0,
    "2016年": 0,
    "2015年": 0,
    "2014年": 0,
    "2013年": 0,
    "2012年": 0,
    "2011年": 0,
    "2010年": 0,
    "2009年": 0,
    "2008年": 0,
    "2007年": 0,
    "2006年": 0,
    "2005年": 0,
    "2004年": 0,
    "2003年": 0,
    "2002年": 0,
    "2001年": 0,
    "2000年": 0,
    "内蒙古": "内蒙古"
  },
  "辽宁": {
    "地区": "辽宁",
    "2019年": 0,
    "2018年": 34.18,
    "2017年": 33.05,
    "2016年": 32.59,
    "2015年": 34.85,
    "2014年": 35.14,
    "2013年": 31.97,
    "2012年": 32.56,
    "2011年": 31.24,
    "2010年": 26.5,
    "2009年": 24.84,
    "2008年": 24.65,
    "2007年": 25.43,
    "2006年": 34.28,
    "2005年": 39.46,
    "2004年": 38.37,
    "2003年": 33.04,
    "2002年": 34.89,
    "2001年": 32.53,
    "2000年": 35.02,
    "辽宁": "辽宁"
  },
  "吉林": {
    "地区": "吉林",
    "2019年": 0,
    "2018年": 0,
    "2017年": 0,
    "2016年": 0,
    "2015年": 0,
    "2014年": 0,
    "2013年": 0,
    "2012年": 0,
    "2011年": 0,
    "2010年": 0,
    "2009年": 0,
    "2008年": 0,
    "2007年": 0,
    "2006年": 0,
    "2005年": 0,
    "2004年": 0,
    "2003年": 0,
    "2002年": 0,
    "2001年": 0,
    "2000年": 0,
    "吉林": "吉林"
  },
  "黑龙江": {
    "地区": "黑龙江",
    "2019年": 0,
    "2018年": 0,
    "2017年": 0,
    "2016年": 0,
    "2015年": 0,
    "2014年": 0,
    "2013年": 0,
    "2012年": 0,
    "2011年": 0,
    "2010年": 0,
    "2009年": 0,
    "2008年": 0,
    "2007年": 0,
    "2006年": 0,
    "2005年": 0,
    "2004年": 0,
    "2003年": 0,
    "2002年": 0,
    "2001年": 0,
    "2000年": 0,
    "黑龙江": "黑龙江"
  },
  "上海": {
    "地区": "上海",
    "2019年": 0,
    "2018年": 0,
    "2017年": 0,
    "2016年": 0,
    "2015年": 0,
    "2014年": 0,
    "2013年": 0,
    "2012年": 0,
    "2011年": 0,
    "2010年": 0,
    "2009年": 0,
    "2008年": 0,
    "2007年": 0,
    "2006年": 0,
    "2005年": 0,
    "2004年": 0,
    "2003年": 0,
    "2002年": 0,
    "2001年": 0,
    "2000年": 0,
    "上海": "上海"
  },
  "江苏": {
    "地区": "江苏",
    "2019年": 0,
    "2018年": 4.34,
    "2017年": 4.35,
    "2016年": 3.01,
    "2015年": 2.93,
    "2014年": 2.83,
    "2013年": 3.09,
    "2012年": 2.42,
    "2011年": 2.6,
    "2010年": 2.99,
    "2009年": 3.35,
    "2008年": 2.63,
    "2007年": 2.92,
    "2006年": 1.92,
    "2005年": 1.87,
    "2004年": 1.74,
    "2003年": 1.43,
    "2002年": 1.09,
    "2001年": 1.08,
    "2000年": 0.84,
    "江苏": "江苏"
  },
  "浙江": {
    "地区": "浙江",
    "2019年": 0,
    "2018年": 8.93,
    "2017年": 7.46,
    "2016年": 5.51,
    "2015年": 5.15,
    "2014年": 4.83,
    "2013年": 4.8,
    "2012年": 4.96,
    "2011年": 4.8,
    "2010年": 4.45,
    "2009年": 4.22,
    "2008年": 3.49,
    "2007年": 4.2,
    "2006年": 4.12,
    "2005年": 3.46,
    "2004年": 4.34,
    "2003年": 3.86,
    "2002年": 3.23,
    "2001年": 2.83,
    "2000年": 2.72,
    "浙江": "浙江"
  },
  "安徽": {
    "地区": "安徽",
    "2019年": 0,
    "2018年": 0,
    "2017年": 0,
    "2016年": 0,
    "2015年": 0,
    "2014年": 0,
    "2013年": 0,
    "2012年": 0,
    "2011年": 0,
    "2010年": 0,
    "2009年": 0,
    "2008年": 0,
    "2007年": 0,
    "2006年": 0,
    "2005年": 0,
    "2004年": 0,
    "2003年": 0,
    "2002年": 0,
    "2001年": 0,
    "2000年": 0,
    "安徽": "安徽"
  },
  "福建": {
    "地区": "福建",
    "2019年": 0,
    "2018年": 112.04,
    "2017年": 103.35,
    "2016年": 98.16,
    "2015年": 89.68,
    "2014年": 81.52,
    "2013年": 77.65,
    "2012年": 71.07,
    "2011年": 63.02,
    "2010年": 59.94,
    "2009年": 55.54,
    "2008年": 51.26,
    "2007年": 46.69,
    "2006年": 50.23,
    "2005年": 46.83,
    "2004年": 44.33,
    "2003年": 41.72,
    "2002年": 38.67,
    "2001年": 34.56,
    "2000年": 31.78,
    "福建": "福建"
  },
  "江西": {
    "地区": "江西",
    "2019年": 0,
    "2018年": 0,
    "2017年": 0,
    "2016年": 0,
    "2015年": 0,
    "2014年": 0,
    "2013年": 0,
    "2012年": 0,
    "2011年": 0,
    "2010年": 0,
    "2009年": 0,
    "2008年": 0,
    "2007年": 0,
    "2006年": 0,
    "2005年": 0,
    "2004年": 0,
    "2003年": 0,
    "2002年": 0,
    "2001年": 0,
    "2000年": 0,
    "江西": "江西"
  },
  "山东": {
    "地区": "山东",
    "2019年": 0,
    "2018年": 66.66,
    "2017年": 66.03,
    "2016年": 67.47,
    "2015年": 66.74,
    "2014年": 66.43,
    "2013年": 59.06,
    "2012年": 56.82,
    "2011年": 50.94,
    "2010年": 53.05,
    "2009年": 50.75,
    "2008年": 51.05,
    "2007年": 51.88,
    "2006年": 53.87,
    "2005年": 53.81,
    "2004年": 53.74,
    "2003年": 53.6,
    "2002年": 47.57,
    "2001年": 47.47,
    "2000年": 45.88,
    "山东": "山东"
  },
  "河南": {
    "地区": "河南",
    "2019年": 0,
    "2018年": 0,
    "2017年": 0,
    "2016年": 0,
    "2015年": 0,
    "2014年": 0,
    "2013年": 0,
    "2012年": 0,
    "2011年": 0,
    "2010年": 0,
    "2009年": 0,
    "2008年": 0,
    "2007年": 0,
    "2006年": 0,
    "2005年": 0,
    "2004年": 0,
    "2003年": 0,
    "2002年": 0,
    "2001年": 0,
    "2000年": 0,
    "河南": "河南"
  },
  "湖北": {
    "地区": "湖北",
    "2019年": 0,
    "2018年": 0,
    "2017年": 0,
    "2016年": 0,
    "2015年": 0,
    "2014年": 0,
    "2013年": 0,
    "2012年": 0,
    "2011年": 0,
    "2010年": 0,
    "2009年": 0,
    "2008年": 0,
    "2007年": 0,
    "2006年": 0,
    "2005年": 0,
    "2004年": 0,
    "2003年": 0,
    "2002年": 0,
    "2001年": 0,
    "2000年": 0,
    "湖北": "湖北"
  },
  "湖南": {
    "地区": "湖南",
    "2019年": 0,
    "2018年": 0,
    "2017年": 0,
    "2016年": 0,
    "2015年": 0,
    "2014年": 0,
    "2013年": 0,
    "2012年": 0,
    "2011年": 0,
    "2010年": 0,
    "2009年": 0,
    "2008年": 0,
    "2007年": 0,
    "2006年": 0,
    "2005年": 0,
    "2004年": 0,
    "2003年": 0,
    "2002年": 0,
    "2001年": 0,
    "2000年": 0,
    "湖南": "湖南"
  },
  "广东": {
    "地区": "广东",
    "2019年": 0,
    "2018年": 7.93,
    "2017年": 8.17,
    "2016年": 8.64,
    "2015年": 8.3,
    "2014年": 8.22,
    "2013年": 8.27,
    "2012年": 7.87,
    "2011年": 7.17,
    "2010年": 6.6,
    "2009年": 6.88,
    "2008年": 6.01,
    "2007年": 4.32,
    "2006年": 4.69,
    "2005年": 3.92,
    "2004年": 3.4,
    "2003年": 3.61,
    "2002年": 3.32,
    "2001年": 2.52,
    "2000年": 2.41,
    "广东": "广东"
  },
  "广西": {
    "地区": "广西",
    "2019年": 0,
    "2018年": 0,
    "2017年": 0,
    "2016年": 0,
    "2015年": 0,
    "2014年": 0,
    "2013年": 0,
    "2012年": 0,
    "2011年": 0,
    "2010年": 0,
    "2009年": 0,
    "2008年": 0,
    "2007年": 0.02,
    "2006年": 0.03,
    "2005年": 0.02,
    "2004年": 0.07,
    "2003年": 0.06,
    "2002年": 0.21,
    "2001年": 0,
    "2000年": 0,
    "广西": "广西"
  },
  "海南": {
    "地区": "海南",
    "2019年": 0,
    "2018年": 2.04,
    "2017年": 2.38,
    "2016年": 3.95,
    "2015年": 3.86,
    "2014年": 3.93,
    "2013年": 3.63,
    "2012年": 3.35,
    "2011年": 3.14,
    "2010年": 3.04,
    "2009年": 2.84,
    "2008年": 3.16,
    "2007年": 3.38,
    "2006年": 4.33,
    "2005年": 4.81,
    "2004年": 4.53,
    "2003年": 3.99,
    "2002年": 4.36,
    "2001年": 3.95,
    "2000年": 3.54,
    "海南": "海南"
  },
  "重庆": {
    "地区": "重庆",
    "2019年": 0,
    "2018年": 0,
    "2017年": 0,
    "2016年": 0,
    "2015年": 0,
    "2014年": 0,
    "2013年": 0,
    "2012年": 0,
    "2011年": 0,
    "2010年": 0,
    "2009年": 0,
    "2008年": 0,
    "2007年": 0,
    "2006年": 0,
    "2005年": 0,
    "2004年": 0,
    "2003年": 0,
    "2002年": 0,
    "2001年": 0,
    "2000年": 0,
    "重庆": "重庆"
  },
  "四川": {
    "地区": "四川",
    "2019年": 0,
    "2018年": 0,
    "2017年": 0,
    "2016年": 0,
    "2015年": 0,
    "2014年": 0,
    "2013年": 0,
    "2012年": 0,
    "2011年": 0,
    "2010年": 0,
    "2009年": 0,
    "2008年": 0,
    "2007年": 0,
    "2006年": 0,
    "2005年": 0,
    "2004年": 0,
    "2003年": 0,
    "2002年": 0,
    "2001年": 0,
    "2000年": 0,
    "四川": "四川"
  },
  "贵州": {
    "地区": "贵州",
    "2019年": 0,
    "2018年": 0,
    "2017年": 0,
    "2016年": 0,
    "2015年": 0,
    "2014年": 0,
    "2013年": 0,
    "2012年": 0,
    "2011年": 0,
    "2010年": 0,
    "2009年": 0,
    "2008年": 0,
    "2007年": 0,
    "2006年": 0,
    "2005年": 0,
    "2004年": 0,
    "2003年": 0,
    "2002年": 0,
    "2001年": 0,
    "2000年": 0,
    "贵州": "贵州"
  },
  "云南": {
    "地区": "云南",
    "2019年": 0,
    "2018年": 0,
    "2017年": 0,
    "2016年": 0,
    "2015年": 0,
    "2014年": 0,
    "2013年": 0,
    "2012年": 0,
    "2011年": 0,
    "2010年": 0,
    "2009年": 0,
    "2008年": 0,
    "2007年": 0,
    "2006年": 0,
    "2005年": 0,
    "2004年": 0,
    "2003年": 0,
    "2002年": 0,
    "2001年": 0,
    "2000年": 0,
    "云南": "云南"
  },
  "西藏": {
    "地区": "西藏",
    "2019年": 0,
    "2018年": 0,
    "2017年": 0,
    "2016年": 0,
    "2015年": 0,
    "2014年": 0,
    "2013年": 0,
    "2012年": 0,
    "2011年": 0,
    "2010年": 0,
    "2009年": 0,
    "2008年": 0,
    "2007年": 0,
    "2006年": 0,
    "2005年": 0,
    "2004年": 0,
    "2003年": 0,
    "2002年": 0,
    "2001年": 0,
    "2000年": 0,
    "西藏": "西藏"
  },
  "陕西": {
    "地区": "陕西",
    "2019年": 0,
    "2018年": 0,
    "2017年": 0,
    "2016年": 0,
    "2015年": 0,
    "2014年": 0,
    "2013年": 0,
    "2012年": 0,
    "2011年": 0,
    "2010年": 0,
    "2009年": 0,
    "2008年": 0,
    "2007年": 0,
    "2006年": 0,
    "2005年": 0,
    "2004年": 0,
    "2003年": 0,
    "2002年": 0,
    "2001年": 0,
    "2000年": 0,
    "陕西": "陕西"
  },
  "甘肃": {
    "地区": "甘肃",
    "2019年": 0,
    "2018年": 0,
    "2017年": 0,
    "2016年": 0,
    "2015年": 0,
    "2014年": 0,
    "2013年": 0,
    "2012年": 0,
    "2011年": 0,
    "2010年": 0,
    "2009年": 0,
    "2008年": 0,
    "2007年": 0,
    "2006年": 0,
    "2005年": 0,
    "2004年": 0,
    "2003年": 0,
    "2002年": 0,
    "2001年": 0,
    "2000年": 0,
    "甘肃": "甘肃"
  },
  "青海": {
    "地区": "青海",
    "2019年": 0,
    "2018年": 0,
    "2017年": 0,
    "2016年": 0,
    "2015年": 0,
    "2014年": 0,
    "2013年": 0,
    "2012年": 0,
    "2011年": 0,
    "2010年": 0,
    "2009年": 0,
    "2008年": 0,
    "2007年": 0,
    "2006年": 0,
    "2005年": 0,
    "2004年": 0,
    "2003年": 0,
    "2002年": 0,
    "2001年": 0,
    "2000年": 0,
    "青海": "青海"
  },
  "宁夏": {
    "地区": "宁夏",
    "2019年": 0,
    "2018年": 0,
    "2017年": 0,
    "2016年": 0,
    "2015年": 0,
    "2014年": 0,
    "2013年": 0,
    "2012年": 0,
    "2011年": 0,
    "2010年": 0,
    "2009年": 0,
    "2008年": 0,
    "2007年": 0,
    "2006年": 0,
    "2005年": 0,
    "2004年": 0,
    "2003年": 0,
    "2002年": 0,
    "2001年": 0,
    "2000年": 0,
    "宁夏": "宁夏"
  },
  "新疆": {
    "地区": "新疆",
    "2019年": 0,
    "2018年": 0,
    "2017年": 0,
    "2016年": 0,
    "2015年": 0,
    "2014年": 0,
    "2013年": 0,
    "2012年": 0,
    "2011年": 0,
    "2010年": 0,
    "2009年": 0,
    "2008年": 0,
    "2007年": 0,
    "2006年": 0,
    "2005年": 0,
    "2004年": 0,
    "2003年": 0,
    "2002年": 0,
    "2001年": 0,
    "2000年": 0,
    "新疆": "新疆"
  }
}