{
  "北京": {
    "地区": "北京",
    "2019年": 0,
    "2018年": 0,
    "2017年": 0,
    "2016年": 0,
    "2015年": 0,
    "2014年": 0,
    "2013年": 0,
    "2012年": 0,
    "2011年": 0,
    "2010年": 0,
    "2009年": 0,
    "2008年": 0,
    "2007年": 0,
    "2006年": 0,
    "2005年": 0,
    "2004年": 0,
    "2003年": 0,
    "2002年": 0,
    "2001年": 0,
    "2000年": 0,
    "北京": "北京"
  },
  "天津": {
    "地区": "天津",
    "2019年": 0,
    "2018年": 0,
    "2017年": 0,
    "2016年": 0,
    "2015年": 0,
    "2014年": 0,
    "2013年": 0,
    "2012年": 0,
    "2011年": 0,
    "2010年": 0,
    "2009年": 0,
    "2008年": 0,
    "2007年": 0,
    "2006年": 0,
    "2005年": 0,
    "2004年": 0,
    "2003年": 0,
    "2002年": 0,
    "2001年": 0,
    "2000年": 0,
    "天津": "天津"
  },
  "河北": {
    "地区": "河北",
    "2019年": 0,
    "2018年": 1146.97,
    "2017年": 0,
    "2016年": 0,
    "2015年": 0,
    "2014年": 0,
    "2013年": 0,
    "2012年": 0,
    "2011年": 0,
    "2010年": 0,
    "2009年": 0,
    "2008年": 0,
    "2007年": 0,
    "2006年": 820,
    "2005年": 560,
    "2004年": 2042.77,
    "2003年": 654.55,
    "2002年": 685.71,
    "2001年": 947.37,
    "2000年": 523.33,
    "河北": "河北"
  },
  "山西": {
    "地区": "山西",
    "2019年": 0,
    "2018年": 2085.89,
    "2017年": 0,
    "2016年": 0,
    "2015年": 2216.87,
    "2014年": 686.05,
    "2013年": 633.33,
    "2012年": 465.75,
    "2011年": 829.79,
    "2010年": 808.51,
    "2009年": 800,
    "2008年": 1000,
    "2007年": 1000,
    "2006年": 1450,
    "2005年": 760,
    "2004年": 1100,
    "2003年": 1689.53,
    "2002年": 317.74,
    "2001年": 394.83,
    "2000年": 1226.42,
    "山西": "山西"
  },
  "内蒙古": {
    "地区": "内蒙古",
    "2019年": 0,
    "2018年": 1557.69,
    "2017年": 5837.39,
    "2016年": 6639.33,
    "2015年": 0,
    "2014年": 0,
    "2013年": 0,
    "2012年": 1000,
    "2011年": 2230.77,
    "2010年": 0,
    "2009年": 0,
    "2008年": 0,
    "2007年": 0,
    "2006年": 913.64,
    "2005年": 918.18,
    "2004年": 889.57,
    "2003年": 2014,
    "2002年": 1601.75,
    "2001年": 445,
    "2000年": 556.88,
    "内蒙古": "内蒙古"
  },
  "辽宁": {
    "地区": "辽宁",
    "2019年": 0,
    "2018年": 0,
    "2017年": 0,
    "2016年": 0,
    "2015年": 0,
    "2014年": 0,
    "2013年": 0,
    "2012年": 0,
    "2011年": 0,
    "2010年": 0,
    "2009年": 0,
    "2008年": 0,
    "2007年": 0,
    "2006年": 1200,
    "2005年": 0,
    "2004年": 0,
    "2003年": 1695,
    "2002年": 1550,
    "2001年": 1266.67,
    "2000年": 940.22,
    "辽宁": "辽宁"
  },
  "吉林": {
    "地区": "吉林",
    "2019年": 0,
    "2018年": 0,
    "2017年": 1937.5,
    "2016年": 2000,
    "2015年": 0,
    "2014年": 1000,
    "2013年": 3000,
    "2012年": 1007.14,
    "2011年": 647.83,
    "2010年": 462.1,
    "2009年": 905.06,
    "2008年": 3475.38,
    "2007年": 2727.3,
    "2006年": 1568.42,
    "2005年": 1875,
    "2004年": 0,
    "2003年": 0,
    "2002年": 1685.29,
    "2001年": 942.31,
    "2000年": 1383.02,
    "吉林": "吉林"
  },
  "黑龙江": {
    "地区": "黑龙江",
    "2019年": 0,
    "2018年": 6396.82,
    "2017年": 6212.7,
    "2016年": 6019.61,
    "2015年": 8736.39,
    "2014年": 9279.69,
    "2013年": 8802.9,
    "2012年": 4129.17,
    "2011年": 4700,
    "2010年": 107.69,
    "2009年": 2074.07,
    "2008年": 2951.32,
    "2007年": 2771.09,
    "2006年": 8956.87,
    "2005年": 7669.42,
    "2004年": 1181.78,
    "2003年": 2940.98,
    "2002年": 1654.14,
    "2001年": 2220.42,
    "2000年": 1094.51,
    "黑龙江": "黑龙江"
  },
  "上海": {
    "地区": "上海",
    "2019年": 0,
    "2018年": 0,
    "2017年": 0,
    "2016年": 0,
    "2015年": 0,
    "2014年": 0,
    "2013年": 0,
    "2012年": 0,
    "2011年": 0,
    "2010年": 0,
    "2009年": 0,
    "2008年": 0,
    "2007年": 0,
    "2006年": 0,
    "2005年": 0,
    "2004年": 0,
    "2003年": 0,
    "2002年": 0,
    "2001年": 0,
    "2000年": 0,
    "上海": "上海"
  },
  "江苏": {
    "地区": "江苏",
    "2019年": 0,
    "2018年": 0,
    "2017年": 7300,
    "2016年": 0,
    "2015年": 7400,
    "2014年": 10300,
    "2013年": 10350,
    "2012年": 13750,
    "2011年": 0,
    "2010年": 0,
    "2009年": 0,
    "2008年": 0,
    "2007年": 0,
    "2006年": 0,
    "2005年": 3600,
    "2004年": 3250,
    "2003年": 1825,
    "2002年": 3110,
    "2001年": 1500,
    "2000年": 1500,
    "江苏": "江苏"
  },
  "浙江": {
    "地区": "浙江",
    "2019年": 0,
    "2018年": 0,
    "2017年": 0,
    "2016年": 0,
    "2015年": 0,
    "2014年": 0,
    "2013年": 0,
    "2012年": 0,
    "2011年": 0,
    "2010年": 0,
    "2009年": 0,
    "2008年": 0,
    "2007年": 0,
    "2006年": 0,
    "2005年": 0,
    "2004年": 0,
    "2003年": 0,
    "2002年": 0,
    "2001年": 0,
    "2000年": 0,
    "浙江": "浙江"
  },
  "安徽": {
    "地区": "安徽",
    "2019年": 0,
    "2018年": 3276.16,
    "2017年": 3218.29,
    "2016年": 3357.51,
    "2015年": 3491.96,
    "2014年": 3253.94,
    "2013年": 3041.27,
    "2012年": 3716.86,
    "2011年": 2653.34,
    "2010年": 3016.54,
    "2009年": 2782,
    "2008年": 3627.35,
    "2007年": 3584.12,
    "2006年": 2786.7,
    "2005年": 2400,
    "2004年": 2584.08,
    "2003年": 2253.37,
    "2002年": 2331.71,
    "2001年": 2417.59,
    "2000年": 2280.82,
    "安徽": "安徽"
  },
  "福建": {
    "地区": "福建",
    "2019年": 0,
    "2018年": 0,
    "2017年": 0,
    "2016年": 0,
    "2015年": 0,
    "2014年": 0,
    "2013年": 0,
    "2012年": 0,
    "2011年": 0,
    "2010年": 0,
    "2009年": 0,
    "2008年": 0,
    "2007年": 0,
    "2006年": 0,
    "2005年": 0,
    "2004年": 0,
    "2003年": 0,
    "2002年": 0,
    "2001年": 0,
    "2000年": 0,
    "福建": "福建"
  },
  "江西": {
    "地区": "江西",
    "2019年": 0,
    "2018年": 1000,
    "2017年": 0,
    "2016年": 0,
    "2015年": 0,
    "2014年": 0,
    "2013年": 0,
    "2012年": 0,
    "2011年": 0,
    "2010年": 0,
    "2009年": 0,
    "2008年": 0,
    "2007年": 0,
    "2006年": 0,
    "2005年": 0,
    "2004年": 0,
    "2003年": 0,
    "2002年": 0,
    "2001年": 0,
    "2000年": 0,
    "江西": "江西"
  },
  "山东": {
    "地区": "山东",
    "2019年": 0,
    "2018年": 2000,
    "2017年": 2028.13,
    "2016年": 2758.38,
    "2015年": 1836.79,
    "2014年": 1886.19,
    "2013年": 1953.84,
    "2012年": 1972.66,
    "2011年": 1965.57,
    "2010年": 1957.36,
    "2009年": 1952.82,
    "2008年": 1870.59,
    "2007年": 1810.34,
    "2006年": 2300,
    "2005年": 2057.14,
    "2004年": 0,
    "2003年": 1857.14,
    "2002年": 2340,
    "2001年": 2614.29,
    "2000年": 0,
    "山东": "山东"
  },
  "河南": {
    "地区": "河南",
    "2019年": 0,
    "2018年": 0,
    "2017年": 0,
    "2016年": 1000,
    "2015年": 5485.29,
    "2014年": 550,
    "2013年": 0,
    "2012年": 2200,
    "2011年": 3900,
    "2010年": 4075,
    "2009年": 4093.96,
    "2008年": 2500,
    "2007年": 3500,
    "2006年": 3180.95,
    "2005年": 3068.18,
    "2004年": 2400,
    "2003年": 2321.62,
    "2002年": 3267.44,
    "2001年": 2725.45,
    "2000年": 2245.92,
    "河南": "河南"
  },
  "湖北": {
    "地区": "湖北",
    "2019年": 0,
    "2018年": 0,
    "2017年": 0,
    "2016年": 0,
    "2015年": 0,
    "2014年": 0,
    "2013年": 0,
    "2012年": 0,
    "2011年": 0,
    "2010年": 0,
    "2009年": 0,
    "2008年": 0,
    "2007年": 0,
    "2006年": 0,
    "2005年": 0,
    "2004年": 0,
    "2003年": 0,
    "2002年": 0,
    "2001年": 0,
    "2000年": 0,
    "湖北": "湖北"
  },
  "湖南": {
    "地区": "湖南",
    "2019年": 0,
    "2018年": 0,
    "2017年": 0,
    "2016年": 0,
    "2015年": 0,
    "2014年": 0,
    "2013年": 0,
    "2012年": 0,
    "2011年": 0,
    "2010年": 0,
    "2009年": 0,
    "2008年": 0,
    "2007年": 0,
    "2006年": 0,
    "2005年": 0,
    "2004年": 0,
    "2003年": 0,
    "2002年": 0,
    "2001年": 0,
    "2000年": 0,
    "湖南": "湖南"
  },
  "广东": {
    "地区": "广东",
    "2019年": 0,
    "2018年": 0,
    "2017年": 0,
    "2016年": 0,
    "2015年": 0,
    "2014年": 0,
    "2013年": 0,
    "2012年": 0,
    "2011年": 0,
    "2010年": 0,
    "2009年": 0,
    "2008年": 0,
    "2007年": 0,
    "2006年": 0,
    "2005年": 0,
    "2004年": 0,
    "2003年": 0,
    "2002年": 0,
    "2001年": 0,
    "2000年": 0,
    "广东": "广东"
  },
  "广西": {
    "地区": "广西",
    "2019年": 0,
    "2018年": 0,
    "2017年": 0,
    "2016年": 0,
    "2015年": 0,
    "2014年": 0,
    "2013年": 0,
    "2012年": 0,
    "2011年": 0,
    "2010年": 0,
    "2009年": 0,
    "2008年": 0,
    "2007年": 0,
    "2006年": 0,
    "2005年": 0,
    "2004年": 0,
    "2003年": 0,
    "2002年": 0,
    "2001年": 0,
    "2000年": 0,
    "广西": "广西"
  },
  "海南": {
    "地区": "海南",
    "2019年": 0,
    "2018年": 0,
    "2017年": 0,
    "2016年": 0,
    "2015年": 0,
    "2014年": 0,
    "2013年": 0,
    "2012年": 0,
    "2011年": 0,
    "2010年": 0,
    "2009年": 0,
    "2008年": 0,
    "2007年": 0,
    "2006年": 0,
    "2005年": 0,
    "2004年": 0,
    "2003年": 0,
    "2002年": 0,
    "2001年": 0,
    "2000年": 0,
    "海南": "海南"
  },
  "重庆": {
    "地区": "重庆",
    "2019年": 0,
    "2018年": 1209.68,
    "2017年": 1022.73,
    "2016年": 914.63,
    "2015年": 918.37,
    "2014年": 954.55,
    "2013年": 923.08,
    "2012年": 900,
    "2011年": 900,
    "2010年": 0,
    "2009年": 0,
    "2008年": 0,
    "2007年": 0,
    "2006年": 0,
    "2005年": 0,
    "2004年": 0,
    "2003年": 0,
    "2002年": 0,
    "2001年": 0,
    "2000年": 0,
    "重庆": "重庆"
  },
  "四川": {
    "地区": "四川",
    "2019年": 0,
    "2018年": 1050,
    "2017年": 1500,
    "2016年": 1153.85,
    "2015年": 1375,
    "2014年": 1000,
    "2013年": 1095.24,
    "2012年": 1081.97,
    "2011年": 1161.29,
    "2010年": 1158.73,
    "2009年": 1063.49,
    "2008年": 927.27,
    "2007年": 2234.04,
    "2006年": 0,
    "2005年": 0,
    "2004年": 0,
    "2003年": 0,
    "2002年": 0,
    "2001年": 0,
    "2000年": 910.81,
    "四川": "四川"
  },
  "贵州": {
    "地区": "贵州",
    "2019年": 0,
    "2018年": 1319.77,
    "2017年": 2653.85,
    "2016年": 2475.61,
    "2015年": 2010.76,
    "2014年": 2057.98,
    "2013年": 2029.42,
    "2012年": 820.9,
    "2011年": 772.16,
    "2010年": 1021.52,
    "2009年": 1020.42,
    "2008年": 961.84,
    "2007年": 1022.07,
    "2006年": 1038.22,
    "2005年": 825.69,
    "2004年": 1080,
    "2003年": 1100,
    "2002年": 946.67,
    "2001年": 996.97,
    "2000年": 1146.67,
    "贵州": "贵州"
  },
  "云南": {
    "地区": "云南",
    "2019年": 0,
    "2018年": 1458.46,
    "2017年": 0,
    "2016年": 0,
    "2015年": 0,
    "2014年": 3919.46,
    "2013年": 3850.54,
    "2012年": 4977.83,
    "2011年": 10034.17,
    "2010年": 5999.03,
    "2009年": 2174.88,
    "2008年": 1050.57,
    "2007年": 2284.22,
    "2006年": 391.94,
    "2005年": 1411.05,
    "2004年": 1248,
    "2003年": 3495.65,
    "2002年": 417.89,
    "2001年": 489.47,
    "2000年": 463.27,
    "云南": "云南"
  },
  "西藏": {
    "地区": "西藏",
    "2019年": 0,
    "2018年": 0,
    "2017年": 0,
    "2016年": 0,
    "2015年": 0,
    "2014年": 0,
    "2013年": 0,
    "2012年": 0,
    "2011年": 0,
    "2010年": 0,
    "2009年": 0,
    "2008年": 0,
    "2007年": 0,
    "2006年": 0,
    "2005年": 0,
    "2004年": 0,
    "2003年": 0,
    "2002年": 0,
    "2001年": 0,
    "2000年": 0,
    "西藏": "西藏"
  },
  "陕西": {
    "地区": "陕西",
    "2019年": 0,
    "2018年": 1286.67,
    "2017年": 1363.64,
    "2016年": 1323.53,
    "2015年": 1000,
    "2014年": 1323.53,
    "2013年": 1323.53,
    "2012年": 1250,
    "2011年": 0,
    "2010年": 0,
    "2009年": 789.47,
    "2008年": 1022.73,
    "2007年": 0,
    "2006年": 1511.74,
    "2005年": 0,
    "2004年": 1148.31,
    "2003年": 1111.57,
    "2002年": 908.11,
    "2001年": 754,
    "2000年": 1326.92,
    "陕西": "陕西"
  },
  "甘肃": {
    "地区": "甘肃",
    "2019年": 0,
    "2018年": 1772.15,
    "2017年": 1696.43,
    "2016年": 1626.51,
    "2015年": 1677.54,
    "2014年": 1568.44,
    "2013年": 1478.54,
    "2012年": 1344.64,
    "2011年": 1195.38,
    "2010年": 1492.4,
    "2009年": 1783.56,
    "2008年": 2051.28,
    "2007年": 2767.3,
    "2006年": 3858.6,
    "2005年": 3986.96,
    "2004年": 2989.56,
    "2003年": 3368.84,
    "2002年": 3293.11,
    "2001年": 1066.95,
    "2000年": 1035.21,
    "甘肃": "甘肃"
  },
  "青海": {
    "地区": "青海",
    "2019年": 0,
    "2018年": 0,
    "2017年": 0,
    "2016年": 0,
    "2015年": 0,
    "2014年": 0,
    "2013年": 0,
    "2012年": 0,
    "2011年": 0,
    "2010年": 0,
    "2009年": 0,
    "2008年": 0,
    "2007年": 0,
    "2006年": 0,
    "2005年": 600,
    "2004年": 0,
    "2003年": 11466.67,
    "2002年": 1112.75,
    "2001年": 0,
    "2000年": 0,
    "青海": "青海"
  },
  "宁夏": {
    "地区": "宁夏",
    "2019年": 0,
    "2018年": 0,
    "2017年": 0,
    "2016年": 0,
    "2015年": 0,
    "2014年": 0,
    "2013年": 0,
    "2012年": 0,
    "2011年": 0,
    "2010年": 0,
    "2009年": 0,
    "2008年": 0,
    "2007年": 1100,
    "2006年": 1100,
    "2005年": 0,
    "2004年": 0,
    "2003年": 0,
    "2002年": 0,
    "2001年": 0,
    "2000年": 1557.14,
    "宁夏": "宁夏"
  },
  "新疆": {
    "地区": "新疆",
    "2019年": 0,
    "2018年": 0,
    "2017年": 0,
    "2016年": 0,
    "2015年": 0,
    "2014年": 0,
    "2013年": 0,
    "2012年": 0,
    "2011年": 0,
    "2010年": 0,
    "2009年": 0,
    "2008年": 0,
    "2007年": 0,
    "2006年": 0,
    "2005年": 0,
    "2004年": 0,
    "2003年": 0,
    "2002年": 0,
    "2001年": 0,
    "2000年": 0,
    "新疆": "新疆"
  }
}