{
  "北京": {
    "地区": "北京",
    "2019年": 0,
    "2018年": 0,
    "2017年": 0,
    "2016年": 31,
    "2015年": 26,
    "2014年": 25,
    "2013年": 25,
    "2012年": 25,
    "2011年": 25,
    "2010年": 25,
    "2009年": 0,
    "2008年": 0,
    "2007年": 0,
    "2006年": 0,
    "2005年": 0,
    "2004年": 0,
    "2003年": 0,
    "2002年": 0,
    "2001年": 0,
    "2000年": 0,
    "北京": "北京"
  },
  "天津": {
    "地区": "天津",
    "2019年": 0,
    "2018年": 0,
    "2017年": 0,
    "2016年": 38,
    "2015年": 39,
    "2014年": 39,
    "2013年": 38,
    "2012年": 38,
    "2011年": 35,
    "2010年": 35,
    "2009年": 0,
    "2008年": 0,
    "2007年": 0,
    "2006年": 0,
    "2005年": 0,
    "2004年": 0,
    "2003年": 0,
    "2002年": 0,
    "2001年": 0,
    "2000年": 0,
    "天津": "天津"
  },
  "河北": {
    "地区": "河北",
    "2019年": 0,
    "2018年": 0,
    "2017年": 0,
    "2016年": 291,
    "2015年": 290,
    "2014年": 290,
    "2013年": 286,
    "2012年": 276,
    "2011年": 267,
    "2010年": 261,
    "2009年": 0,
    "2008年": 0,
    "2007年": 0,
    "2006年": 0,
    "2005年": 0,
    "2004年": 0,
    "2003年": 0,
    "2002年": 0,
    "2001年": 0,
    "2000年": 0,
    "河北": "河北"
  },
  "山西": {
    "地区": "山西",
    "2019年": 0,
    "2018年": 0,
    "2017年": 0,
    "2016年": 215,
    "2015年": 211,
    "2014年": 212,
    "2013年": 209,
    "2012年": 208,
    "2011年": 208,
    "2010年": 190,
    "2009年": 0,
    "2008年": 0,
    "2007年": 0,
    "2006年": 0,
    "2005年": 0,
    "2004年": 0,
    "2003年": 0,
    "2002年": 0,
    "2001年": 0,
    "2000年": 0,
    "山西": "山西"
  },
  "内蒙古": {
    "地区": "内蒙古",
    "2019年": 0,
    "2018年": 0,
    "2017年": 0,
    "2016年": 1011,
    "2015年": 985,
    "2014年": 1121,
    "2013年": 1105,
    "2012年": 1047,
    "2011年": 1005,
    "2010年": 886,
    "2009年": 0,
    "2008年": 0,
    "2007年": 0,
    "2006年": 0,
    "2005年": 0,
    "2004年": 0,
    "2003年": 0,
    "2002年": 0,
    "2001年": 0,
    "2000年": 0,
    "内蒙古": "内蒙古"
  },
  "辽宁": {
    "地区": "辽宁",
    "2019年": 0,
    "2018年": 0,
    "2017年": 0,
    "2016年": 273,
    "2015年": 269,
    "2014年": 363,
    "2013年": 366,
    "2012年": 360,
    "2011年": 350,
    "2010年": 348,
    "2009年": 0,
    "2008年": 0,
    "2007年": 0,
    "2006年": 0,
    "2005年": 0,
    "2004年": 0,
    "2003年": 0,
    "2002年": 0,
    "2001年": 0,
    "2000年": 0,
    "辽宁": "辽宁"
  },
  "吉林": {
    "地区": "吉林",
    "2019年": 0,
    "2018年": 0,
    "2017年": 0,
    "2016年": 331,
    "2015年": 314,
    "2014年": 291,
    "2013年": 280,
    "2012年": 273,
    "2011年": 268,
    "2010年": 262,
    "2009年": 0,
    "2008年": 0,
    "2007年": 0,
    "2006年": 0,
    "2005年": 0,
    "2004年": 0,
    "2003年": 0,
    "2002年": 0,
    "2001年": 0,
    "2000年": 0,
    "吉林": "吉林"
  },
  "黑龙江": {
    "地区": "黑龙江",
    "2019年": 0,
    "2018年": 0,
    "2017年": 0,
    "2016年": 599,
    "2015年": 580,
    "2014年": 540,
    "2013年": 536,
    "2012年": 403,
    "2011年": 395,
    "2010年": 375,
    "2009年": 0,
    "2008年": 0,
    "2007年": 0,
    "2006年": 0,
    "2005年": 0,
    "2004年": 0,
    "2003年": 0,
    "2002年": 0,
    "2001年": 0,
    "2000年": 0,
    "黑龙江": "黑龙江"
  },
  "上海": {
    "地区": "上海",
    "2019年": 0,
    "2018年": 0,
    "2017年": 0,
    "2016年": 27,
    "2015年": 27,
    "2014年": 26,
    "2013年": 26,
    "2012年": 26,
    "2011年": 21,
    "2010年": 21,
    "2009年": 0,
    "2008年": 0,
    "2007年": 0,
    "2006年": 0,
    "2005年": 0,
    "2004年": 0,
    "2003年": 0,
    "2002年": 0,
    "2001年": 0,
    "2000年": 0,
    "上海": "上海"
  },
  "江苏": {
    "地区": "江苏",
    "2019年": 0,
    "2018年": 0,
    "2017年": 0,
    "2016年": 267,
    "2015年": 252,
    "2014年": 224,
    "2013年": 209,
    "2012年": 209,
    "2011年": 202,
    "2010年": 195,
    "2009年": 0,
    "2008年": 0,
    "2007年": 0,
    "2006年": 0,
    "2005年": 0,
    "2004年": 0,
    "2003年": 0,
    "2002年": 0,
    "2001年": 0,
    "2000年": 0,
    "江苏": "江苏"
  },
  "浙江": {
    "地区": "浙江",
    "2019年": 0,
    "2018年": 0,
    "2017年": 0,
    "2016年": 265,
    "2015年": 265,
    "2014年": 264,
    "2013年": 262,
    "2012年": 257,
    "2011年": 228,
    "2010年": 241,
    "2009年": 0,
    "2008年": 0,
    "2007年": 0,
    "2006年": 0,
    "2005年": 0,
    "2004年": 0,
    "2003年": 0,
    "2002年": 0,
    "2001年": 0,
    "2000年": 0,
    "浙江": "浙江"
  },
  "安徽": {
    "地区": "安徽",
    "2019年": 0,
    "2018年": 0,
    "2017年": 0,
    "2016年": 514,
    "2015年": 585,
    "2014年": 547,
    "2013年": 595,
    "2012年": 598,
    "2011年": 616,
    "2010年": 676,
    "2009年": 0,
    "2008年": 0,
    "2007年": 0,
    "2006年": 0,
    "2005年": 0,
    "2004年": 0,
    "2003年": 0,
    "2002年": 0,
    "2001年": 0,
    "2000年": 0,
    "安徽": "安徽"
  },
  "福建": {
    "地区": "福建",
    "2019年": 0,
    "2018年": 0,
    "2017年": 0,
    "2016年": 256,
    "2015年": 259,
    "2014年": 258,
    "2013年": 257,
    "2012年": 257,
    "2011年": 261,
    "2010年": 255,
    "2009年": 0,
    "2008年": 0,
    "2007年": 0,
    "2006年": 0,
    "2005年": 0,
    "2004年": 0,
    "2003年": 0,
    "2002年": 0,
    "2001年": 0,
    "2000年": 0,
    "福建": "福建"
  },
  "江西": {
    "地区": "江西",
    "2019年": 0,
    "2018年": 0,
    "2017年": 0,
    "2016年": 474,
    "2015年": 481,
    "2014年": 539,
    "2013年": 553,
    "2012年": 737,
    "2011年": 738,
    "2010年": 781,
    "2009年": 0,
    "2008年": 0,
    "2007年": 0,
    "2006年": 0,
    "2005年": 0,
    "2004年": 0,
    "2003年": 0,
    "2002年": 0,
    "2001年": 0,
    "2000年": 0,
    "江西": "江西"
  },
  "山东": {
    "地区": "山东",
    "2019年": 0,
    "2018年": 0,
    "2017年": 0,
    "2016年": 253,
    "2015年": 237,
    "2014年": 238,
    "2013年": 243,
    "2012年": 236,
    "2011年": 231,
    "2010年": 227,
    "2009年": 0,
    "2008年": 0,
    "2007年": 0,
    "2006年": 0,
    "2005年": 0,
    "2004年": 0,
    "2003年": 0,
    "2002年": 0,
    "2001年": 0,
    "2000年": 0,
    "山东": "山东"
  },
  "河南": {
    "地区": "河南",
    "2019年": 0,
    "2018年": 0,
    "2017年": 0,
    "2016年": 190,
    "2015年": 190,
    "2014年": 190,
    "2013年": 190,
    "2012年": 189,
    "2011年": 189,
    "2010年": 189,
    "2009年": 0,
    "2008年": 0,
    "2007年": 0,
    "2006年": 0,
    "2005年": 0,
    "2004年": 0,
    "2003年": 0,
    "2002年": 0,
    "2001年": 0,
    "2000年": 0,
    "河南": "河南"
  },
  "湖北": {
    "地区": "湖北",
    "2019年": 0,
    "2018年": 0,
    "2017年": 0,
    "2016年": 486,
    "2015年": 716,
    "2014年": 611,
    "2013年": 609,
    "2012年": 604,
    "2011年": 598,
    "2010年": 584,
    "2009年": 0,
    "2008年": 0,
    "2007年": 0,
    "2006年": 0,
    "2005年": 0,
    "2004年": 0,
    "2003年": 0,
    "2002年": 0,
    "2001年": 0,
    "2000年": 0,
    "湖北": "湖北"
  },
  "湖南": {
    "地区": "湖南",
    "2019年": 0,
    "2018年": 0,
    "2017年": 0,
    "2016年": 186,
    "2015年": 186,
    "2014年": 175,
    "2013年": 173,
    "2012年": 167,
    "2011年": 167,
    "2010年": 161,
    "2009年": 0,
    "2008年": 0,
    "2007年": 0,
    "2006年": 0,
    "2005年": 0,
    "2004年": 0,
    "2003年": 0,
    "2002年": 0,
    "2001年": 0,
    "2000年": 0,
    "湖南": "湖南"
  },
  "广东": {
    "地区": "广东",
    "2019年": 0,
    "2018年": 0,
    "2017年": 0,
    "2016年": 288,
    "2015年": 248,
    "2014年": 255,
    "2013年": 278,
    "2012年": 288,
    "2011年": 278,
    "2010年": 258,
    "2009年": 0,
    "2008年": 0,
    "2007年": 0,
    "2006年": 0,
    "2005年": 0,
    "2004年": 0,
    "2003年": 0,
    "2002年": 0,
    "2001年": 0,
    "2000年": 0,
    "广东": "广东"
  },
  "广西": {
    "地区": "广西",
    "2019年": 0,
    "2018年": 0,
    "2017年": 0,
    "2016年": 1528,
    "2015年": 1305,
    "2014年": 905,
    "2013年": 642,
    "2012年": 397,
    "2011年": 370,
    "2010年": 345,
    "2009年": 0,
    "2008年": 0,
    "2007年": 0,
    "2006年": 0,
    "2005年": 0,
    "2004年": 0,
    "2003年": 0,
    "2002年": 0,
    "2001年": 0,
    "2000年": 0,
    "广西": "广西"
  },
  "海南": {
    "地区": "海南",
    "2019年": 0,
    "2018年": 0,
    "2017年": 0,
    "2016年": 82,
    "2015年": 82,
    "2014年": 59,
    "2013年": 60,
    "2012年": 95,
    "2011年": 95,
    "2010年": 95,
    "2009年": 0,
    "2008年": 0,
    "2007年": 0,
    "2006年": 0,
    "2005年": 0,
    "2004年": 0,
    "2003年": 0,
    "2002年": 0,
    "2001年": 0,
    "2000年": 0,
    "海南": "海南"
  },
  "重庆": {
    "地区": "重庆",
    "2019年": 0,
    "2018年": 0,
    "2017年": 0,
    "2016年": 262,
    "2015年": 255,
    "2014年": 253,
    "2013年": 261,
    "2012年": 260,
    "2011年": 260,
    "2010年": 254,
    "2009年": 0,
    "2008年": 0,
    "2007年": 0,
    "2006年": 0,
    "2005年": 0,
    "2004年": 0,
    "2003年": 0,
    "2002年": 0,
    "2001年": 0,
    "2000年": 0,
    "重庆": "重庆"
  },
  "四川": {
    "地区": "四川",
    "2019年": 0,
    "2018年": 0,
    "2017年": 0,
    "2016年": 739,
    "2015年": 719,
    "2014年": 731,
    "2013年": 2152,
    "2012年": 2832,
    "2011年": 2776,
    "2010年": 2901,
    "2009年": 0,
    "2008年": 0,
    "2007年": 0,
    "2006年": 0,
    "2005年": 0,
    "2004年": 0,
    "2003年": 0,
    "2002年": 0,
    "2001年": 0,
    "2000年": 0,
    "四川": "四川"
  },
  "贵州": {
    "地区": "贵州",
    "2019年": 0,
    "2018年": 0,
    "2017年": 0,
    "2016年": 398,
    "2015年": 397,
    "2014年": 385,
    "2013年": 384,
    "2012年": 392,
    "2011年": 305,
    "2010年": 288,
    "2009年": 0,
    "2008年": 0,
    "2007年": 0,
    "2006年": 0,
    "2005年": 0,
    "2004年": 0,
    "2003年": 0,
    "2002年": 0,
    "2001年": 0,
    "2000年": 0,
    "贵州": "贵州"
  },
  "云南": {
    "地区": "云南",
    "2019年": 0,
    "2018年": 0,
    "2017年": 0,
    "2016年": 972,
    "2015年": 897,
    "2014年": 811,
    "2013年": 799,
    "2012年": 822,
    "2011年": 869,
    "2010年": 843,
    "2009年": 0,
    "2008年": 0,
    "2007年": 0,
    "2006年": 0,
    "2005年": 0,
    "2004年": 0,
    "2003年": 0,
    "2002年": 0,
    "2001年": 0,
    "2000年": 0,
    "云南": "云南"
  },
  "西藏": {
    "地区": "西藏",
    "2019年": 0,
    "2018年": 0,
    "2017年": 0,
    "2016年": 5153,
    "2015年": 5153,
    "2014年": 5151,
    "2013年": 5151,
    "2012年": 5151,
    "2011年": 5150,
    "2010年": 5148,
    "2009年": 0,
    "2008年": 0,
    "2007年": 0,
    "2006年": 0,
    "2005年": 0,
    "2004年": 0,
    "2003年": 0,
    "2002年": 0,
    "2001年": 0,
    "2000年": 0,
    "西藏": "西藏"
  },
  "陕西": {
    "地区": "陕西",
    "2019年": 0,
    "2018年": 0,
    "2017年": 0,
    "2016年": 394,
    "2015年": 383,
    "2014年": 381,
    "2013年": 378,
    "2012年": 383,
    "2011年": 314,
    "2010年": 244,
    "2009年": 0,
    "2008年": 0,
    "2007年": 0,
    "2006年": 0,
    "2005年": 0,
    "2004年": 0,
    "2003年": 0,
    "2002年": 0,
    "2001年": 0,
    "2000年": 0,
    "陕西": "陕西"
  },
  "甘肃": {
    "地区": "甘肃",
    "2019年": 0,
    "2018年": 0,
    "2017年": 0,
    "2016年": 702,
    "2015年": 773,
    "2014年": 894,
    "2013年": 985,
    "2012年": 981,
    "2011年": 967,
    "2010年": 949,
    "2009年": 0,
    "2008年": 0,
    "2007年": 0,
    "2006年": 0,
    "2005年": 0,
    "2004年": 0,
    "2003年": 0,
    "2002年": 0,
    "2001年": 0,
    "2000年": 0,
    "甘肃": "甘肃"
  },
  "青海": {
    "地区": "青海",
    "2019年": 0,
    "2018年": 0,
    "2017年": 0,
    "2016年": 616,
    "2015年": 592,
    "2014年": 393,
    "2013年": 333,
    "2012年": 340,
    "2011年": 333,
    "2010年": 328,
    "2009年": 0,
    "2008年": 0,
    "2007年": 0,
    "2006年": 0,
    "2005年": 0,
    "2004年": 0,
    "2003年": 0,
    "2002年": 0,
    "2001年": 0,
    "2000年": 0,
    "青海": "青海"
  },
  "宁夏": {
    "地区": "宁夏",
    "2019年": 0,
    "2018年": 0,
    "2017年": 0,
    "2016年": 61,
    "2015年": 73,
    "2014年": 70,
    "2013年": 64,
    "2012年": 64,
    "2011年": 64,
    "2010年": 64,
    "2009年": 0,
    "2008年": 0,
    "2007年": 0,
    "2006年": 0,
    "2005年": 0,
    "2004年": 0,
    "2003年": 0,
    "2002年": 0,
    "2001年": 0,
    "2000年": 0,
    "宁夏": "宁夏"
  },
  "新疆": {
    "地区": "新疆",
    "2019年": 0,
    "2018年": 0,
    "2017年": 0,
    "2016年": 1533,
    "2015年": 1575,
    "2014年": 1653,
    "2013年": 1604,
    "2012年": 1484,
    "2011年": 1497,
    "2010年": 1487,
    "2009年": 0,
    "2008年": 0,
    "2007年": 0,
    "2006年": 0,
    "2005年": 0,
    "2004年": 0,
    "2003年": 0,
    "2002年": 0,
    "2001年": 0,
    "2000年": 0,
    "新疆": "新疆"
  }
}