{
  "北京": {
    "地区": "北京",
    "2019年": 0,
    "2018年": 100,
    "2017年": 100,
    "2016年": 100,
    "2015年": 100,
    "2014年": 100,
    "2013年": 100,
    "2012年": 100,
    "2011年": 100,
    "2010年": 100,
    "2009年": 100,
    "2008年": 100,
    "2007年": 100,
    "2006年": 123.36,
    "2005年": 100,
    "2004年": 100,
    "2003年": 0,
    "2002年": 0,
    "2001年": 0,
    "2000年": 0,
    "北京": "北京"
  },
  "天津": {
    "地区": "天津",
    "2019年": 0,
    "2018年": 100,
    "2017年": 100,
    "2016年": 100,
    "2015年": 100,
    "2014年": 100,
    "2013年": 100,
    "2012年": 100,
    "2011年": 100,
    "2010年": 100,
    "2009年": 100,
    "2008年": 100,
    "2007年": 100,
    "2006年": 100.26,
    "2005年": 100,
    "2004年": 100,
    "2003年": 0,
    "2002年": 0,
    "2001年": 0,
    "2000年": 0,
    "天津": "天津"
  },
  "河北": {
    "地区": "河北",
    "2019年": 0,
    "2018年": 99.7,
    "2017年": 99.05,
    "2016年": 99.52,
    "2015年": 99.56,
    "2014年": 99.29,
    "2013年": 99.85,
    "2012年": 99.96,
    "2011年": 100,
    "2010年": 99.97,
    "2009年": 99.97,
    "2008年": 99.97,
    "2007年": 99.97,
    "2006年": 92.01,
    "2005年": 99.95,
    "2004年": 99.94,
    "2003年": 0,
    "2002年": 0,
    "2001年": 0,
    "2000年": 0,
    "河北": "河北"
  },
  "山西": {
    "地区": "山西",
    "2019年": 0,
    "2018年": 99.7,
    "2017年": 97.81,
    "2016年": 99.29,
    "2015年": 98.85,
    "2014年": 98.54,
    "2013年": 98.14,
    "2012年": 97.64,
    "2011年": 97.48,
    "2010年": 97.26,
    "2009年": 95.38,
    "2008年": 93.27,
    "2007年": 92.96,
    "2006年": 89.58,
    "2005年": 90.32,
    "2004年": 85.62,
    "2003年": 0,
    "2002年": 0,
    "2001年": 0,
    "2000年": 0,
    "山西": "山西"
  },
  "内蒙古": {
    "地区": "内蒙古",
    "2019年": 0,
    "2018年": 99.23,
    "2017年": 99.1,
    "2016年": 98.98,
    "2015年": 98.47,
    "2014年": 97.79,
    "2013年": 96.23,
    "2012年": 94.43,
    "2011年": 91.39,
    "2010年": 87.97,
    "2009年": 87.89,
    "2008年": 82.03,
    "2007年": 81.45,
    "2006年": 80.67,
    "2005年": 83.88,
    "2004年": 82.21,
    "2003年": 0,
    "2002年": 0,
    "2001年": 0,
    "2000年": 0,
    "内蒙古": "内蒙古"
  },
  "辽宁": {
    "地区": "辽宁",
    "2019年": 0,
    "2018年": 99.16,
    "2017年": 98.45,
    "2016年": 98.96,
    "2015年": 98.84,
    "2014年": 98.72,
    "2013年": 98.77,
    "2012年": 98.45,
    "2011年": 98.36,
    "2010年": 97.44,
    "2009年": 97.23,
    "2008年": 96.89,
    "2007年": 96.94,
    "2006年": 92.14,
    "2005年": 93.83,
    "2004年": 92.99,
    "2003年": 0,
    "2002年": 0,
    "2001年": 0,
    "2000年": 0,
    "辽宁": "辽宁"
  },
  "吉林": {
    "地区": "吉林",
    "2019年": 0,
    "2018年": 93.89,
    "2017年": 94.85,
    "2016年": 93.4,
    "2015年": 93.64,
    "2014年": 93.79,
    "2013年": 93.84,
    "2012年": 92.38,
    "2011年": 92.71,
    "2010年": 89.6,
    "2009年": 88.75,
    "2008年": 88.63,
    "2007年": 88.03,
    "2006年": 80.53,
    "2005年": 83.2,
    "2004年": 77.25,
    "2003年": 0,
    "2002年": 0,
    "2001年": 0,
    "2000年": 0,
    "吉林": "吉林"
  },
  "黑龙江": {
    "地区": "黑龙江",
    "2019年": 0,
    "2018年": 98.48,
    "2017年": 98.53,
    "2016年": 97.25,
    "2015年": 97.2,
    "2014年": 96.2,
    "2013年": 95.46,
    "2012年": 94.14,
    "2011年": 90.78,
    "2010年": 88.43,
    "2009年": 86.56,
    "2008年": 84.24,
    "2007年": 81.84,
    "2006年": 79.2,
    "2005年": 79.55,
    "2004年": 80.77,
    "2003年": 0,
    "2002年": 0,
    "2001年": 0,
    "2000年": 0,
    "黑龙江": "黑龙江"
  },
  "上海": {
    "地区": "上海",
    "2019年": 0,
    "2018年": 100,
    "2017年": 100,
    "2016年": 100,
    "2015年": 100,
    "2014年": 100,
    "2013年": 100,
    "2012年": 100,
    "2011年": 100,
    "2010年": 100,
    "2009年": 100,
    "2008年": 100,
    "2007年": 100,
    "2006年": 100,
    "2005年": 99.98,
    "2004年": 100,
    "2003年": 0,
    "2002年": 0,
    "2001年": 0,
    "2000年": 0,
    "上海": "上海"
  },
  "江苏": {
    "地区": "江苏",
    "2019年": 0,
    "2018年": 99.98,
    "2017年": 99.98,
    "2016年": 99.86,
    "2015年": 99.83,
    "2014年": 99.75,
    "2013年": 99.69,
    "2012年": 99.7,
    "2011年": 99.58,
    "2010年": 99.56,
    "2009年": 99.65,
    "2008年": 99.88,
    "2007年": 99.47,
    "2006年": 81.99,
    "2005年": 96.28,
    "2004年": 94,
    "2003年": 0,
    "2002年": 0,
    "2001年": 0,
    "2000年": 0,
    "江苏": "江苏"
  },
  "浙江": {
    "地区": "浙江",
    "2019年": 0,
    "2018年": 100,
    "2017年": 100,
    "2016年": 99.97,
    "2015年": 99.95,
    "2014年": 99.93,
    "2013年": 99.97,
    "2012年": 99.88,
    "2011年": 99.84,
    "2010年": 99.79,
    "2009年": 99.81,
    "2008年": 99.7,
    "2007年": 99.58,
    "2006年": 70.96,
    "2005年": 99.1,
    "2004年": 98.86,
    "2003年": 0,
    "2002年": 0,
    "2001年": 0,
    "2000年": 0,
    "浙江": "浙江"
  },
  "安徽": {
    "地区": "安徽",
    "2019年": 0,
    "2018年": 99.75,
    "2017年": 99.43,
    "2016年": 99.2,
    "2015年": 98.79,
    "2014年": 98.63,
    "2013年": 98.4,
    "2012年": 98.02,
    "2011年": 96.55,
    "2010年": 96.06,
    "2009年": 95.25,
    "2008年": 95.11,
    "2007年": 94.4,
    "2006年": 89.93,
    "2005年": 90.52,
    "2004年": 89.95,
    "2003年": 0,
    "2002年": 0,
    "2001年": 0,
    "2000年": 0,
    "安徽": "安徽"
  },
  "福建": {
    "地区": "福建",
    "2019年": 0,
    "2018年": 99.69,
    "2017年": 99.56,
    "2016年": 99.52,
    "2015年": 99.55,
    "2014年": 99.49,
    "2013年": 99.42,
    "2012年": 99.13,
    "2011年": 99.11,
    "2010年": 99.5,
    "2009年": 99.18,
    "2008年": 97.47,
    "2007年": 98.86,
    "2006年": 78.37,
    "2005年": 98.68,
    "2004年": 95.9,
    "2003年": 0,
    "2002年": 0,
    "2001年": 0,
    "2000年": 0,
    "福建": "福建"
  },
  "江西": {
    "地区": "江西",
    "2019年": 0,
    "2018年": 98.31,
    "2017年": 98.11,
    "2016年": 97.69,
    "2015年": 97.55,
    "2014年": 97.78,
    "2013年": 97.73,
    "2012年": 97.67,
    "2011年": 97.94,
    "2010年": 97.43,
    "2009年": 98,
    "2008年": 96.49,
    "2007年": 94.59,
    "2006年": 91.34,
    "2005年": 92.64,
    "2004年": 92.24,
    "2003年": 0,
    "2002年": 0,
    "2001年": 0,
    "2000年": 0,
    "江西": "江西"
  },
  "山东": {
    "地区": "山东",
    "2019年": 0,
    "2018年": 99.4,
    "2017年": 99.82,
    "2016年": 99.78,
    "2015年": 99.95,
    "2014年": 99.92,
    "2013年": 99.85,
    "2012年": 99.85,
    "2011年": 99.74,
    "2010年": 99.57,
    "2009年": 99.47,
    "2008年": 99.39,
    "2007年": 98.79,
    "2006年": 97.17,
    "2005年": 77.39,
    "2004年": 75.46,
    "2003年": 0,
    "2002年": 0,
    "2001年": 0,
    "2000年": 0,
    "山东": "山东"
  },
  "河南": {
    "地区": "河南",
    "2019年": 0,
    "2018年": 96.65,
    "2017年": 95.88,
    "2016年": 93.42,
    "2015年": 93.1,
    "2014年": 92.99,
    "2013年": 92.16,
    "2012年": 91.76,
    "2011年": 92.64,
    "2010年": 91.03,
    "2009年": 88.34,
    "2008年": 85.56,
    "2007年": 88.63,
    "2006年": 87.16,
    "2005年": 91.94,
    "2004年": 92.14,
    "2003年": 0,
    "2002年": 0,
    "2001年": 0,
    "2000年": 0,
    "河南": "河南"
  },
  "湖北": {
    "地区": "湖北",
    "2019年": 0,
    "2018年": 99.37,
    "2017年": 99.27,
    "2016年": 99.12,
    "2015年": 98.83,
    "2014年": 98.75,
    "2013年": 98.19,
    "2012年": 98.24,
    "2011年": 98.25,
    "2010年": 97.59,
    "2009年": 97.45,
    "2008年": 97.88,
    "2007年": 97.56,
    "2006年": 91.45,
    "2005年": 77.62,
    "2004年": 73.75,
    "2003年": 0,
    "2002年": 0,
    "2001年": 0,
    "2000年": 0,
    "湖北": "湖北"
  },
  "湖南": {
    "地区": "湖南",
    "2019年": 0,
    "2018年": 96.35,
    "2017年": 96.52,
    "2016年": 96.81,
    "2015年": 97.3,
    "2014年": 97.05,
    "2013年": 96.86,
    "2012年": 96.42,
    "2011年": 95.68,
    "2010年": 95.17,
    "2009年": 94.82,
    "2008年": 94.57,
    "2007年": 93.71,
    "2006年": 90.27,
    "2005年": 91.11,
    "2004年": 87.61,
    "2003年": 0,
    "2002年": 0,
    "2001年": 0,
    "2000年": 0,
    "湖南": "湖南"
  },
  "广东": {
    "地区": "广东",
    "2019年": 0,
    "2018年": 97.3,
    "2017年": 97.8,
    "2016年": 98.06,
    "2015年": 98.46,
    "2014年": 97.26,
    "2013年": 97.47,
    "2012年": 97.62,
    "2011年": 98.39,
    "2010年": 98.37,
    "2009年": 97.7,
    "2008年": 93.97,
    "2007年": 84.8,
    "2006年": 76.6,
    "2005年": 98.8,
    "2004年": 95.14,
    "2003年": 0,
    "2002年": 0,
    "2001年": 0,
    "2000年": 0,
    "广东": "广东"
  },
  "广西": {
    "地区": "广西",
    "2019年": 0,
    "2018年": 97.8,
    "2017年": 97.63,
    "2016年": 97.7,
    "2015年": 97.5,
    "2014年": 94.4,
    "2013年": 95.91,
    "2012年": 95.3,
    "2011年": 93.91,
    "2010年": 94.65,
    "2009年": 94.43,
    "2008年": 92.87,
    "2007年": 91.89,
    "2006年": 79.85,
    "2005年": 82.28,
    "2004年": 78.74,
    "2003年": 0,
    "2002年": 0,
    "2001年": 0,
    "2000年": 0,
    "广西": "广西"
  },
  "海南": {
    "地区": "海南",
    "2019年": 0,
    "2018年": 97.04,
    "2017年": 98.4,
    "2016年": 97.41,
    "2015年": 98.64,
    "2014年": 98.1,
    "2013年": 98.38,
    "2012年": 97.74,
    "2011年": 96.09,
    "2010年": 89.43,
    "2009年": 89.65,
    "2008年": 83.87,
    "2007年": 77.15,
    "2006年": 80.4,
    "2005年": 85.97,
    "2004年": 89.64,
    "2003年": 0,
    "2002年": 0,
    "2001年": 0,
    "2000年": 0,
    "海南": "海南"
  },
  "重庆": {
    "地区": "重庆",
    "2019年": 0,
    "2018年": 98.28,
    "2017年": 98.05,
    "2016年": 97.13,
    "2015年": 96.87,
    "2014年": 96.78,
    "2013年": 96.25,
    "2012年": 93.84,
    "2011年": 93.41,
    "2010年": 94.05,
    "2009年": 94.6,
    "2008年": 93.2,
    "2007年": 91.49,
    "2006年": 81.38,
    "2005年": 79.38,
    "2004年": 76.81,
    "2003年": 0,
    "2002年": 0,
    "2001年": 0,
    "2000年": 0,
    "重庆": "重庆"
  },
  "四川": {
    "地区": "四川",
    "2019年": 0,
    "2018年": 95.7,
    "2017年": 94.91,
    "2016年": 93.07,
    "2015年": 93.05,
    "2014年": 91.12,
    "2013年": 91.76,
    "2012年": 92.04,
    "2011年": 91.83,
    "2010年": 90.8,
    "2009年": 89.68,
    "2008年": 88.09,
    "2007年": 86.55,
    "2006年": 80.83,
    "2005年": 97.22,
    "2004年": 97.49,
    "2003年": 0,
    "2002年": 0,
    "2001年": 0,
    "2000年": 0,
    "四川": "四川"
  },
  "贵州": {
    "地区": "贵州",
    "2019年": 0,
    "2018年": 96.68,
    "2017年": 96.54,
    "2016年": 96.03,
    "2015年": 95.43,
    "2014年": 94.47,
    "2013年": 92.86,
    "2012年": 92.07,
    "2011年": 91.55,
    "2010年": 94.1,
    "2009年": 92.09,
    "2008年": 88.69,
    "2007年": 82.52,
    "2006年": 84.24,
    "2005年": 92.75,
    "2004年": 88.6,
    "2003年": 0,
    "2002年": 0,
    "2001年": 0,
    "2000年": 0,
    "贵州": "贵州"
  },
  "云南": {
    "地区": "云南",
    "2019年": 0,
    "2018年": 96.6,
    "2017年": 96.71,
    "2016年": 96.66,
    "2015年": 97.33,
    "2014年": 97.85,
    "2013年": 97.92,
    "2012年": 94.32,
    "2011年": 95.09,
    "2010年": 96.5,
    "2009年": 96.23,
    "2008年": 95.22,
    "2007年": 95.41,
    "2006年": 74.46,
    "2005年": 82.07,
    "2004年": 81.5,
    "2003年": 0,
    "2002年": 0,
    "2001年": 0,
    "2000年": 0,
    "云南": "云南"
  },
  "西藏": {
    "地区": "西藏",
    "2019年": 0,
    "2018年": 85.9,
    "2017年": 92.8,
    "2016年": 67.57,
    "2015年": 88.06,
    "2014年": 89.07,
    "2013年": 96.95,
    "2012年": 75.39,
    "2011年": 91.93,
    "2010年": 97.42,
    "2009年": 92.53,
    "2008年": 86.59,
    "2007年": 90.58,
    "2006年": 48.63,
    "2005年": 61.82,
    "2004年": 69.01,
    "2003年": 0,
    "2002年": 0,
    "2001年": 0,
    "2000年": 0,
    "西藏": "西藏"
  },
  "陕西": {
    "地区": "陕西",
    "2019年": 0,
    "2018年": 95.49,
    "2017年": 95.95,
    "2016年": 95.61,
    "2015年": 97.12,
    "2014年": 96.31,
    "2013年": 96.52,
    "2012年": 96.15,
    "2011年": 95.72,
    "2010年": 99.39,
    "2009年": 98.06,
    "2008年": 96.65,
    "2007年": 95.7,
    "2006年": 85.66,
    "2005年": 93.24,
    "2004年": 94.43,
    "2003年": 0,
    "2002年": 0,
    "2001年": 0,
    "2000年": 0,
    "陕西": "陕西"
  },
  "甘肃": {
    "地区": "甘肃",
    "2019年": 0,
    "2018年": 97.9,
    "2017年": 98.81,
    "2016年": 97.93,
    "2015年": 97.28,
    "2014年": 94.95,
    "2013年": 93.68,
    "2012年": 92.77,
    "2011年": 92.5,
    "2010年": 91.57,
    "2009年": 89.66,
    "2008年": 87.85,
    "2007年": 91.76,
    "2006年": 88.66,
    "2005年": 85.94,
    "2004年": 85.15,
    "2003年": 0,
    "2002年": 0,
    "2001年": 0,
    "2000年": 0,
    "甘肃": "甘肃"
  },
  "青海": {
    "地区": "青海",
    "2019年": 0,
    "2018年": 99,
    "2017年": 98.93,
    "2016年": 99.21,
    "2015年": 99.06,
    "2014年": 99.71,
    "2013年": 99.08,
    "2012年": 99.9,
    "2011年": 99.86,
    "2010年": 99.87,
    "2009年": 99.45,
    "2008年": 100,
    "2007年": 100,
    "2006年": 91.28,
    "2005年": 100,
    "2004年": 99.94,
    "2003年": 0,
    "2002年": 0,
    "2001年": 0,
    "2000年": 0,
    "青海": "青海"
  },
  "宁夏": {
    "地区": "宁夏",
    "2019年": 0,
    "2018年": 98.4,
    "2017年": 95.66,
    "2016年": 94.75,
    "2015年": 96.4,
    "2014年": 97.26,
    "2013年": 96.51,
    "2012年": 92.3,
    "2011年": 95.45,
    "2010年": 98.23,
    "2009年": 97.2,
    "2008年": 87.25,
    "2007年": 90.07,
    "2006年": 84.03,
    "2005年": 62.89,
    "2004年": 61.1,
    "2003年": 0,
    "2002年": 0,
    "2001年": 0,
    "2000年": 0,
    "宁夏": "宁夏"
  },
  "新疆": {
    "地区": "新疆",
    "2019年": 0,
    "2018年": 97.66,
    "2017年": 98.75,
    "2016年": 98.86,
    "2015年": 98.81,
    "2014年": 98.15,
    "2013年": 98.08,
    "2012年": 99.13,
    "2011年": 99.17,
    "2010年": 99.17,
    "2009年": 99.03,
    "2008年": 92.82,
    "2007年": 99.12,
    "2006年": 90.5,
    "2005年": 97.86,
    "2004年": 98.12,
    "2003年": 0,
    "2002年": 0,
    "2001年": 0,
    "2000年": 0,
    "新疆": "新疆"
  }
}