{
  "北京": {
    "地区": "北京",
    "2019年": 0,
    "2018年": 0,
    "2017年": 0,
    "2016年": 0,
    "2015年": 0,
    "2014年": 0,
    "2013年": 0,
    "2012年": 1361133.2,
    "2011年": 1151508,
    "2010年": 1014352,
    "2009年": 1018576.3,
    "2008年": 116445.5,
    "2007年": 481296.4,
    "2006年": 432891,
    "2005年": 372072.6,
    "2004年": 0,
    "2003年": 0,
    "2002年": 0,
    "2001年": 0,
    "2000年": 0,
    "北京": "北京"
  },
  "天津": {
    "地区": "天津",
    "2019年": 0,
    "2018年": 0,
    "2017年": 0,
    "2016年": 0,
    "2015年": 0,
    "2014年": 0,
    "2013年": 0,
    "2012年": 216595.2,
    "2011年": 160160.6,
    "2010年": 139549,
    "2009年": 111561.4,
    "2008年": 83367,
    "2007年": 49015.7,
    "2006年": 37829.9,
    "2005年": 9785.4,
    "2004年": 0,
    "2003年": 0,
    "2002年": 0,
    "2001年": 0,
    "2000年": 0,
    "天津": "天津"
  },
  "河北": {
    "地区": "河北",
    "2019年": 0,
    "2018年": 0,
    "2017年": 0,
    "2016年": 0,
    "2015年": 0,
    "2014年": 0,
    "2013年": 0,
    "2012年": 163704.6,
    "2011年": 117040.1,
    "2010年": 75551,
    "2009年": 48852.6,
    "2008年": 5011.1,
    "2007年": 7869.4,
    "2006年": 4231.6,
    "2005年": 3848.3,
    "2004年": 0,
    "2003年": 0,
    "2002年": 0,
    "2001年": 0,
    "2000年": 0,
    "河北": "河北"
  },
  "山西": {
    "地区": "山西",
    "2019年": 0,
    "2018年": 0,
    "2017年": 0,
    "2016年": 0,
    "2015年": 0,
    "2014年": 0,
    "2013年": 0,
    "2012年": 225603.7,
    "2011年": 126934.2,
    "2010年": 114337,
    "2009年": 57184.2,
    "2008年": 42738.7,
    "2007年": 40462.5,
    "2006年": 13775,
    "2005年": 27217.9,
    "2004年": 0,
    "2003年": 0,
    "2002年": 0,
    "2001年": 0,
    "2000年": 0,
    "山西": "山西"
  },
  "内蒙古": {
    "地区": "内蒙古",
    "2019年": 0,
    "2018年": 0,
    "2017年": 0,
    "2016年": 0,
    "2015年": 0,
    "2014年": 0,
    "2013年": 0,
    "2012年": 5339.9,
    "2011年": 7101.4,
    "2010年": 6020,
    "2009年": 5282.2,
    "2008年": 2958,
    "2007年": 667.3,
    "2006年": 60.6,
    "2005年": 14.3,
    "2004年": 0,
    "2003年": 0,
    "2002年": 0,
    "2001年": 0,
    "2000年": 0,
    "内蒙古": "内蒙古"
  },
  "辽宁": {
    "地区": "辽宁",
    "2019年": 0,
    "2018年": 0,
    "2017年": 0,
    "2016年": 0,
    "2015年": 0,
    "2014年": 0,
    "2013年": 0,
    "2012年": 215852.4,
    "2011年": 175798.2,
    "2010年": 150884,
    "2009年": 131121.1,
    "2008年": 132368,
    "2007年": 165883,
    "2006年": 72739,
    "2005年": 29682.5,
    "2004年": 0,
    "2003年": 0,
    "2002年": 0,
    "2001年": 0,
    "2000年": 0,
    "辽宁": "辽宁"
  },
  "吉林": {
    "地区": "吉林",
    "2019年": 0,
    "2018年": 0,
    "2017年": 0,
    "2016年": 0,
    "2015年": 0,
    "2014年": 0,
    "2013年": 0,
    "2012年": 42902,
    "2011年": 302485.3,
    "2010年": 74498,
    "2009年": 13990.2,
    "2008年": 8574.1,
    "2007年": 11851.1,
    "2006年": 11867,
    "2005年": 14998.2,
    "2004年": 0,
    "2003年": 0,
    "2002年": 0,
    "2001年": 0,
    "2000年": 0,
    "吉林": "吉林"
  },
  "黑龙江": {
    "地区": "黑龙江",
    "2019年": 0,
    "2018年": 0,
    "2017年": 0,
    "2016年": 0,
    "2015年": 0,
    "2014年": 0,
    "2013年": 0,
    "2012年": 31622.2,
    "2011年": 38014.2,
    "2010年": -8788,
    "2009年": 9032.5,
    "2008年": 39259.7,
    "2007年": 7393.1,
    "2006年": 6410.3,
    "2005年": 3540.4,
    "2004年": 0,
    "2003年": 0,
    "2002年": 0,
    "2001年": 0,
    "2000年": 0,
    "黑龙江": "黑龙江"
  },
  "上海": {
    "地区": "上海",
    "2019年": 0,
    "2018年": 0,
    "2017年": 0,
    "2016年": 0,
    "2015年": 0,
    "2014年": 0,
    "2013年": 0,
    "2012年": 392301,
    "2011年": 397510.8,
    "2010年": 379340,
    "2009年": 371531.1,
    "2008年": 229878.4,
    "2007年": 159481,
    "2006年": 97224,
    "2005年": 53447.6,
    "2004年": 0,
    "2003年": 0,
    "2002年": 0,
    "2001年": 0,
    "2000年": 0,
    "上海": "上海"
  },
  "江苏": {
    "地区": "江苏",
    "2019年": 0,
    "2018年": 0,
    "2017年": 0,
    "2016年": 0,
    "2015年": 0,
    "2014年": 0,
    "2013年": 0,
    "2012年": 1394960.5,
    "2011年": 1043684.6,
    "2010年": 826074,
    "2009年": 619078.1,
    "2008年": 510744.2,
    "2007年": 458062,
    "2006年": 346336,
    "2005年": 153785,
    "2004年": 0,
    "2003年": 0,
    "2002年": 0,
    "2001年": 0,
    "2000年": 0,
    "江苏": "江苏"
  },
  "浙江": {
    "地区": "浙江",
    "2019年": 0,
    "2018年": 0,
    "2017年": 0,
    "2016年": 0,
    "2015年": 0,
    "2014年": 0,
    "2013年": 0,
    "2012年": 848776,
    "2011年": 747799.8,
    "2010年": 554782,
    "2009年": 483285.4,
    "2008年": 421590.4,
    "2007年": 403759.1,
    "2006年": 306703.3,
    "2005年": 231056.5,
    "2004年": 0,
    "2003年": 0,
    "2002年": 0,
    "2001年": 0,
    "2000年": 0,
    "浙江": "浙江"
  },
  "安徽": {
    "地区": "安徽",
    "2019年": 0,
    "2018年": 0,
    "2017年": 0,
    "2016年": 0,
    "2015年": 0,
    "2014年": 0,
    "2013年": 0,
    "2012年": 88390.5,
    "2011年": 130000.6,
    "2010年": 133764,
    "2009年": 68605.5,
    "2008年": 129388.8,
    "2007年": 56817.6,
    "2006年": 35536.9,
    "2005年": 9916.6,
    "2004年": 0,
    "2003年": 0,
    "2002年": 0,
    "2001年": 0,
    "2000年": 0,
    "安徽": "安徽"
  },
  "福建": {
    "地区": "福建",
    "2019年": 0,
    "2018年": 0,
    "2017年": 0,
    "2016年": 0,
    "2015年": 0,
    "2014年": 0,
    "2013年": 0,
    "2012年": 37240.4,
    "2011年": 30532.8,
    "2010年": 32296,
    "2009年": 27692.3,
    "2008年": 36242.3,
    "2007年": 26005.8,
    "2006年": 29731.9,
    "2005年": 15700.5,
    "2004年": 0,
    "2003年": 0,
    "2002年": 0,
    "2001年": 0,
    "2000年": 0,
    "福建": "福建"
  },
  "江西": {
    "地区": "江西",
    "2019年": 0,
    "2018年": 0,
    "2017年": 0,
    "2016年": 0,
    "2015年": 0,
    "2014年": 0,
    "2013年": 0,
    "2012年": 19914.5,
    "2011年": 6710,
    "2010年": 638,
    "2009年": 936.6,
    "2008年": 318.6,
    "2007年": 0,
    "2006年": 0,
    "2005年": -0.8,
    "2004年": 0,
    "2003年": 0,
    "2002年": 0,
    "2001年": 0,
    "2000年": 0,
    "江西": "江西"
  },
  "山东": {
    "地区": "山东",
    "2019年": 0,
    "2018年": 0,
    "2017年": 0,
    "2016年": 0,
    "2015年": 0,
    "2014年": 0,
    "2013年": 0,
    "2012年": 229626.4,
    "2011年": 185037.2,
    "2010年": 118214,
    "2009年": 103639.7,
    "2008年": 88808.9,
    "2007年": 86314,
    "2006年": 56552.6,
    "2005年": 26876.2,
    "2004年": 0,
    "2003年": 0,
    "2002年": 0,
    "2001年": 0,
    "2000年": 0,
    "山东": "山东"
  },
  "河南": {
    "地区": "河南",
    "2019年": 0,
    "2018年": 0,
    "2017年": 0,
    "2016年": 0,
    "2015年": 0,
    "2014年": 0,
    "2013年": 0,
    "2012年": 325765.3,
    "2011年": 285847.7,
    "2010年": 178248,
    "2009年": 148488.6,
    "2008年": 94325.5,
    "2007年": 65229.1,
    "2006年": 15587.2,
    "2005年": 8849.7,
    "2004年": 0,
    "2003年": 0,
    "2002年": 0,
    "2001年": 0,
    "2000年": 0,
    "河南": "河南"
  },
  "湖北": {
    "地区": "湖北",
    "2019年": 0,
    "2018年": 0,
    "2017年": 0,
    "2016年": 0,
    "2015年": 0,
    "2014年": 0,
    "2013年": 0,
    "2012年": 775611.7,
    "2011年": 812947.8,
    "2010年": 670289,
    "2009年": 509659.8,
    "2008年": 230211.3,
    "2007年": 257071.2,
    "2006年": 73218.9,
    "2005年": 35123,
    "2004年": 0,
    "2003年": 0,
    "2002年": 0,
    "2001年": 0,
    "2000年": 0,
    "湖北": "湖北"
  },
  "湖南": {
    "地区": "湖南",
    "2019年": 0,
    "2018年": 0,
    "2017年": 0,
    "2016年": 0,
    "2015年": 0,
    "2014年": 0,
    "2013年": 0,
    "2012年": 320895.4,
    "2011年": 271216,
    "2010年": 166068,
    "2009年": 102920.3,
    "2008年": 81734.3,
    "2007年": 59630.2,
    "2006年": 41798.2,
    "2005年": 13532.7,
    "2004年": 0,
    "2003年": 0,
    "2002年": 0,
    "2001年": 0,
    "2000年": 0,
    "湖南": "湖南"
  },
  "广东": {
    "地区": "广东",
    "2019年": 0,
    "2018年": 0,
    "2017年": 0,
    "2016年": 0,
    "2015年": 0,
    "2014年": 0,
    "2013年": 0,
    "2012年": 273036.7,
    "2011年": 251269.5,
    "2010年": 255756,
    "2009年": 165719.2,
    "2008年": 171887.9,
    "2007年": 69871.5,
    "2006年": 46476.4,
    "2005年": 38626.6,
    "2004年": 0,
    "2003年": 0,
    "2002年": 0,
    "2001年": 0,
    "2000年": 0,
    "广东": "广东"
  },
  "广西": {
    "地区": "广西",
    "2019年": 0,
    "2018年": 0,
    "2017年": 0,
    "2016年": 0,
    "2015年": 0,
    "2014年": 0,
    "2013年": 0,
    "2012年": 15465.6,
    "2011年": 14084.2,
    "2010年": 12703,
    "2009年": 5795.4,
    "2008年": 3984.6,
    "2007年": 3055.2,
    "2006年": 1994,
    "2005年": 1385.9,
    "2004年": 0,
    "2003年": 0,
    "2002年": 0,
    "2001年": 0,
    "2000年": 0,
    "广西": "广西"
  },
  "海南": {
    "地区": "海南",
    "2019年": 0,
    "2018年": 0,
    "2017年": 0,
    "2016年": 0,
    "2015年": 0,
    "2014年": 0,
    "2013年": 0,
    "2012年": 113.9,
    "2011年": 33.5,
    "2010年": 810,
    "2009年": 346.8,
    "2008年": 213.3,
    "2007年": 0,
    "2006年": 0,
    "2005年": 0,
    "2004年": 0,
    "2003年": 0,
    "2002年": 0,
    "2001年": 0,
    "2000年": 0,
    "海南": "海南"
  },
  "重庆": {
    "地区": "重庆",
    "2019年": 0,
    "2018年": 0,
    "2017年": 0,
    "2016年": 0,
    "2015年": 0,
    "2014年": 0,
    "2013年": 0,
    "2012年": 33398.2,
    "2011年": 33223.2,
    "2010年": 16789,
    "2009年": 33586.2,
    "2008年": 10508.3,
    "2007年": 14647.3,
    "2006年": 0,
    "2005年": 0,
    "2004年": 0,
    "2003年": 0,
    "2002年": 0,
    "2001年": 0,
    "2000年": 0,
    "重庆": "重庆"
  },
  "四川": {
    "地区": "四川",
    "2019年": 0,
    "2018年": 0,
    "2017年": 0,
    "2016年": 0,
    "2015年": 0,
    "2014年": 0,
    "2013年": 0,
    "2012年": 495336.6,
    "2011年": 213484.1,
    "2010年": 126696,
    "2009年": 53661.2,
    "2008年": 30861.7,
    "2007年": 29186.2,
    "2006年": 12321.3,
    "2005年": 5510.1,
    "2004年": 0,
    "2003年": 0,
    "2002年": 0,
    "2001年": 0,
    "2000年": 0,
    "四川": "四川"
  },
  "贵州": {
    "地区": "贵州",
    "2019年": 0,
    "2018年": 0,
    "2017年": 0,
    "2016年": 0,
    "2015年": 0,
    "2014年": 0,
    "2013年": 0,
    "2012年": 1584.3,
    "2011年": 2176.8,
    "2010年": 3607,
    "2009年": 1043.3,
    "2008年": 593.2,
    "2007年": 456.3,
    "2006年": 408,
    "2005年": 408.2,
    "2004年": 0,
    "2003年": 0,
    "2002年": 0,
    "2001年": 0,
    "2000年": 0,
    "贵州": "贵州"
  },
  "云南": {
    "地区": "云南",
    "2019年": 0,
    "2018年": 0,
    "2017年": 0,
    "2016年": 0,
    "2015年": 0,
    "2014年": 0,
    "2013年": 0,
    "2012年": 74641.9,
    "2011年": 66936,
    "2010年": 55061,
    "2009年": 38794,
    "2008年": 41166.9,
    "2007年": 18525.6,
    "2006年": 12709.2,
    "2005年": 3758.4,
    "2004年": 0,
    "2003年": 0,
    "2002年": 0,
    "2001年": 0,
    "2000年": 0,
    "云南": "云南"
  },
  "西藏": {
    "地区": "西藏",
    "2019年": 0,
    "2018年": 0,
    "2017年": 0,
    "2016年": 0,
    "2015年": 0,
    "2014年": 0,
    "2013年": 0,
    "2012年": 99.6,
    "2011年": 41,
    "2010年": 1180,
    "2009年": 500.2,
    "2008年": -92,
    "2007年": 212.9,
    "2006年": 0,
    "2005年": 0,
    "2004年": 0,
    "2003年": 0,
    "2002年": 0,
    "2001年": 0,
    "2000年": 0,
    "西藏": "西藏"
  },
  "陕西": {
    "地区": "陕西",
    "2019年": 0,
    "2018年": 0,
    "2017年": 0,
    "2016年": 0,
    "2015年": 0,
    "2014年": 0,
    "2013年": 0,
    "2012年": 126223.1,
    "2011年": 97984.4,
    "2010年": 136458,
    "2009年": 186313.3,
    "2008年": 68480,
    "2007年": 74362.5,
    "2006年": 30838.6,
    "2005年": 12412.3,
    "2004年": 0,
    "2003年": 0,
    "2002年": 0,
    "2001年": 0,
    "2000年": 0,
    "陕西": "陕西"
  },
  "甘肃": {
    "地区": "甘肃",
    "2019年": 0,
    "2018年": 0,
    "2017年": 0,
    "2016年": 0,
    "2015年": 0,
    "2014年": 0,
    "2013年": 0,
    "2012年": 43857.9,
    "2011年": 3406,
    "2010年": 11006,
    "2009年": 1773.7,
    "2008年": 7791.8,
    "2007年": 26.4,
    "2006年": -255.2,
    "2005年": 0,
    "2004年": 0,
    "2003年": 0,
    "2002年": 0,
    "2001年": 0,
    "2000年": 0,
    "甘肃": "甘肃"
  },
  "青海": {
    "地区": "青海",
    "2019年": 0,
    "2018年": 0,
    "2017年": 0,
    "2016年": 0,
    "2015年": 0,
    "2014年": 0,
    "2013年": 0,
    "2012年": 50856.2,
    "2011年": 8095.7,
    "2010年": 10148,
    "2009年": 19197.9,
    "2008年": 25250.2,
    "2007年": 22678.8,
    "2006年": 10060.5,
    "2005年": 5505.5,
    "2004年": 0,
    "2003年": 0,
    "2002年": 0,
    "2001年": 0,
    "2000年": 0,
    "青海": "青海"
  },
  "宁夏": {
    "地区": "宁夏",
    "2019年": 0,
    "2018年": 0,
    "2017年": 0,
    "2016年": 0,
    "2015年": 0,
    "2014年": 0,
    "2013年": 0,
    "2012年": 0,
    "2011年": 0,
    "2010年": 0,
    "2009年": 0,
    "2008年": 0,
    "2007年": 0,
    "2006年": 0,
    "2005年": 0,
    "2004年": 0,
    "2003年": 0,
    "2002年": 0,
    "2001年": 0,
    "2000年": 0,
    "宁夏": "宁夏"
  },
  "新疆": {
    "地区": "新疆",
    "2019年": 0,
    "2018年": 0,
    "2017年": 0,
    "2016年": 0,
    "2015年": 0,
    "2014年": 0,
    "2013年": 0,
    "2012年": 2794.1,
    "2011年": 2708.8,
    "2010年": 2162,
    "2009年": 2108.8,
    "2008年": 1319.7,
    "2007年": 533.4,
    "2006年": 1828.5,
    "2005年": 2229.6,
    "2004年": 0,
    "2003年": 0,
    "2002年": 0,
    "2001年": 0,
    "2000年": 0,
    "新疆": "新疆"
  }
}